{
    "area": {
        "new_death": 11,
        "new_population": -28,
        "new_birth": 11,
        "sum_death": 82,
        "sum_population": -73,
        "sum_birth": 47
    },
    "cunli": {
        "潭南村": {
            "11012": "773",
            "11104": "781",
            "11105": "779",
            "11101_birth_total": "0",
            "11101_death_total": "0",
            "11102_birth_total": "0",
            "11102_death_total": "0",
            "11103_birth_total": "1",
            "11103_death_total": "3",
            "11104_birth_total": "0",
            "11104_death_total": "0",
            "11105_birth_total": "0",
            "11105_death_total": "1",
            "new_population": -2,
            "sum_population": 6
        },
        "人和村": {
            "11012": "1460",
            "11104": "1470",
            "11105": "1465",
            "11101_birth_total": "0",
            "11101_death_total": "2",
            "11102_birth_total": "0",
            "11102_death_total": "1",
            "11103_birth_total": "3",
            "11103_death_total": "1",
            "11104_birth_total": "0",
            "11104_death_total": "0",
            "11105_birth_total": "2",
            "11105_death_total": "0",
            "new_population": -5,
            "sum_population": 5
        },
        "新鄉村": {
            "11012": "768",
            "11104": "767",
            "11105": "769",
            "11101_birth_total": "0",
            "11101_death_total": "0",
            "11102_birth_total": "0",
            "11102_death_total": "1",
            "11103_birth_total": "0",
            "11103_death_total": "0",
            "11104_birth_total": "1",
            "11104_death_total": "1",
            "11105_birth_total": "2",
            "11105_death_total": "1",
            "new_population": 2,
            "sum_population": 1
        },
        "地利村": {
            "11012": "1165",
            "11104": "1165",
            "11105": "1164",
            "11101_birth_total": "0",
            "11101_death_total": "4",
            "11102_birth_total": "2",
            "11102_death_total": "1",
            "11103_birth_total": "0",
            "11103_death_total": "3",
            "11104_birth_total": "1",
            "11104_death_total": "1",
            "11105_birth_total": "0",
            "11105_death_total": "1",
            "new_population": -1,
            "sum_population": -1
        },
        "同富村": {
            "11012": "1612",
            "11104": "1618",
            "11105": "1611",
            "11101_birth_total": "0",
            "11101_death_total": "1",
            "11102_birth_total": "0",
            "11102_death_total": "2",
            "11103_birth_total": "2",
            "11103_death_total": "2",
            "11104_birth_total": "0",
            "11104_death_total": "0",
            "11105_birth_total": "0",
            "11105_death_total": "3",
            "new_population": -7,
            "sum_population": -1
        },
        "神木村": {
            "11012": "710",
            "11104": "706",
            "11105": "709",
            "11101_birth_total": "0",
            "11101_death_total": "0",
            "11102_birth_total": "0",
            "11102_death_total": "1",
            "11103_birth_total": "0",
            "11103_death_total": "2",
            "11104_birth_total": "0",
            "11104_death_total": "2",
            "11105_birth_total": "0",
            "11105_death_total": "0",
            "new_population": 3,
            "sum_population": -1
        },
        "愛國村": {
            "11012": "534",
            "11104": "530",
            "11105": "531",
            "11101_birth_total": "0",
            "11101_death_total": "0",
            "11102_birth_total": "0",
            "11102_death_total": "1",
            "11103_birth_total": "0",
            "11103_death_total": "2",
            "11104_birth_total": "0",
            "11104_death_total": "1",
            "11105_birth_total": "0",
            "11105_death_total": "0",
            "new_population": 1,
            "sum_population": -3
        },
        "豐丘村": {
            "11012": "739",
            "11104": "735",
            "11105": "736",
            "11101_birth_total": "0",
            "11101_death_total": "2",
            "11102_birth_total": "0",
            "11102_death_total": "1",
            "11103_birth_total": "0",
            "11103_death_total": "0",
            "11104_birth_total": "1",
            "11104_death_total": "0",
            "11105_birth_total": "0",
            "11105_death_total": "0",
            "new_population": 1,
            "sum_population": -3
        },
        "望美村": {
            "11012": "1899",
            "11104": "1895",
            "11105": "1895",
            "11101_birth_total": "3",
            "11101_death_total": "2",
            "11102_birth_total": "3",
            "11102_death_total": "0",
            "11103_birth_total": "0",
            "11103_death_total": "0",
            "11104_birth_total": "2",
            "11104_death_total": "0",
            "11105_birth_total": "3",
            "11105_death_total": "0",
            "new_population": 0,
            "sum_population": -4
        },
        "羅娜村": {
            "11012": "1668",
            "11104": "1665",
            "11105": "1662",
            "11101_birth_total": "3",
            "11101_death_total": "2",
            "11102_birth_total": "2",
            "11102_death_total": "3",
            "11103_birth_total": "2",
            "11103_death_total": "1",
            "11104_birth_total": "0",
            "11104_death_total": "1",
            "11105_birth_total": "2",
            "11105_death_total": "2",
            "new_population": -3,
            "sum_population": -6
        },
        "雙龍村": {
            "11012": "796",
            "11104": "792",
            "11105": "789",
            "11101_birth_total": "0",
            "11101_death_total": "1",
            "11102_birth_total": "1",
            "11102_death_total": "0",
            "11103_birth_total": "0",
            "11103_death_total": "0",
            "11104_birth_total": "1",
            "11104_death_total": "1",
            "11105_birth_total": "1",
            "11105_death_total": "0",
            "new_population": -3,
            "sum_population": -7
        },
        "自強村": {
            "11012": "785",
            "11104": "771",
            "11105": "769",
            "11101_birth_total": "0",
            "11101_death_total": "0",
            "11102_birth_total": "1",
            "11102_death_total": "3",
            "11103_birth_total": "0",
            "11103_death_total": "6",
            "11104_birth_total": "0",
            "11104_death_total": "1",
            "11105_birth_total": "0",
            "11105_death_total": "1",
            "new_population": -2,
            "sum_population": -16
        },
        "東埔村": {
            "11012": "1223",
            "11104": "1208",
            "11105": "1205",
            "11101_birth_total": "1",
            "11101_death_total": "0",
            "11102_birth_total": "1",
            "11102_death_total": "1",
            "11103_birth_total": "0",
            "11103_death_total": "1",
            "11104_birth_total": "2",
            "11104_death_total": "1",
            "11105_birth_total": "1",
            "11105_death_total": "0",
            "new_population": -3,
            "sum_population": -18
        },
        "明德村": {
            "11012": "1653",
            "11104": "1637",
            "11105": "1628",
            "11101_birth_total": "0",
            "11101_death_total": "2",
            "11102_birth_total": "1",
            "11102_death_total": "4",
            "11103_birth_total": "2",
            "11103_death_total": "1",
            "11104_birth_total": "0",
            "11104_death_total": "5",
            "11105_birth_total": "0",
            "11105_death_total": "2",
            "new_population": -9,
            "sum_population": -25
        }
    }
}