{
    "area": {
        "new_death": 184,
        "new_population": -268,
        "new_birth": 75,
        "sum_death": 742,
        "sum_population": -1610,
        "sum_birth": 331
    },
    "cunli": {
        "公館里": {
            "11012": "1659",
            "11104": "1705",
            "11105": "1709",
            "11101_birth_total": "0",
            "11101_death_total": "2",
            "11102_birth_total": "0",
            "11102_death_total": "1",
            "11103_birth_total": "1",
            "11103_death_total": "2",
            "11104_birth_total": "3",
            "11104_death_total": "2",
            "11105_birth_total": "0",
            "11105_death_total": "1",
            "new_population": 4,
            "sum_population": 50
        },
        "北勢里": {
            "11012": "2671",
            "11104": "2700",
            "11105": "2713",
            "11101_birth_total": "1",
            "11101_death_total": "4",
            "11102_birth_total": "0",
            "11102_death_total": "1",
            "11103_birth_total": "0",
            "11103_death_total": "3",
            "11104_birth_total": "1",
            "11104_death_total": "1",
            "11105_birth_total": "1",
            "11105_death_total": "2",
            "new_population": 13,
            "sum_population": 42
        },
        "和興里": {
            "11012": "1131",
            "11104": "1144",
            "11105": "1153",
            "11101_birth_total": "2",
            "11101_death_total": "0",
            "11102_birth_total": "0",
            "11102_death_total": "0",
            "11103_birth_total": "0",
            "11103_death_total": "0",
            "11104_birth_total": "0",
            "11104_death_total": "2",
            "11105_birth_total": "1",
            "11105_death_total": "1",
            "new_population": 9,
            "sum_population": 22
        },
        "湖南里": {
            "11012": "1201",
            "11104": "1201",
            "11105": "1211",
            "11101_birth_total": "0",
            "11101_death_total": "2",
            "11102_birth_total": "1",
            "11102_death_total": "2",
            "11103_birth_total": "0",
            "11103_death_total": "1",
            "11104_birth_total": "1",
            "11104_death_total": "0",
            "11105_birth_total": "1",
            "11105_death_total": "1",
            "new_population": 10,
            "sum_population": 10
        },
        "龍華里": {
            "11012": "2542",
            "11104": "2551",
            "11105": "2550",
            "11101_birth_total": "0",
            "11101_death_total": "0",
            "11102_birth_total": "0",
            "11102_death_total": "1",
            "11103_birth_total": "0",
            "11103_death_total": "1",
            "11104_birth_total": "2",
            "11104_death_total": "2",
            "11105_birth_total": "0",
            "11105_death_total": "2",
            "new_population": -1,
            "sum_population": 8
        },
        "頂柳里": {
            "11012": "1226",
            "11104": "1231",
            "11105": "1232",
            "11101_birth_total": "1",
            "11101_death_total": "0",
            "11102_birth_total": "0",
            "11102_death_total": "1",
            "11103_birth_total": "0",
            "11103_death_total": "1",
            "11104_birth_total": "1",
            "11104_death_total": "1",
            "11105_birth_total": "2",
            "11105_death_total": "3",
            "new_population": 1,
            "sum_population": 6
        },
        "長安里": {
            "11012": "2866",
            "11104": "2874",
            "11105": "2869",
            "11101_birth_total": "1",
            "11101_death_total": "0",
            "11102_birth_total": "0",
            "11102_death_total": "2",
            "11103_birth_total": "1",
            "11103_death_total": "5",
            "11104_birth_total": "2",
            "11104_death_total": "1",
            "11105_birth_total": "0",
            "11105_death_total": "3",
            "new_population": -5,
            "sum_population": 3
        },
        "金泉里": {
            "11012": "1276",
            "11104": "1273",
            "11105": "1278",
            "11101_birth_total": "0",
            "11101_death_total": "3",
            "11102_birth_total": "0",
            "11102_death_total": "2",
            "11103_birth_total": "0",
            "11103_death_total": "1",
            "11104_birth_total": "0",
            "11104_death_total": "2",
            "11105_birth_total": "0",
            "11105_death_total": "1",
            "new_population": 5,
            "sum_population": 2
        },
        "信和里": {
            "11012": "1799",
            "11104": "1799",
            "11105": "1800",
            "11101_birth_total": "1",
            "11101_death_total": "3",
            "11102_birth_total": "0",
            "11102_death_total": "1",
            "11103_birth_total": "0",
            "11103_death_total": "0",
            "11104_birth_total": "0",
            "11104_death_total": "0",
            "11105_birth_total": "1",
            "11105_death_total": "1",
            "new_population": 1,
            "sum_population": 1
        },
        "頂宅里": {
            "11012": "563",
            "11104": "553",
            "11105": "563",
            "11101_birth_total": "0",
            "11101_death_total": "0",
            "11102_birth_total": "0",
            "11102_death_total": "0",
            "11103_birth_total": "0",
            "11103_death_total": "1",
            "11104_birth_total": "0",
            "11104_death_total": "0",
            "11105_birth_total": "0",
            "11105_death_total": "1",
            "new_population": 10,
            "sum_population": 0
        },
        "三山里": {
            "11012": "1482",
            "11104": "1477",
            "11105": "1482",
            "11101_birth_total": "0",
            "11101_death_total": "1",
            "11102_birth_total": "1",
            "11102_death_total": "3",
            "11103_birth_total": "0",
            "11103_death_total": "0",
            "11104_birth_total": "0",
            "11104_death_total": "0",
            "11105_birth_total": "0",
            "11105_death_total": "0",
            "new_population": 5,
            "sum_population": 0
        },
        "永安里": {
            "11012": "6810",
            "11104": "6813",
            "11105": "6809",
            "11101_birth_total": "2",
            "11101_death_total": "4",
            "11102_birth_total": "2",
            "11102_death_total": "7",
            "11103_birth_total": "6",
            "11103_death_total": "8",
            "11104_birth_total": "2",
            "11104_death_total": "2",
            "11105_birth_total": "1",
            "11105_death_total": "5",
            "new_population": -4,
            "sum_population": -1
        },
        "玉成里": {
            "11012": "1747",
            "11104": "1740",
            "11105": "1746",
            "11101_birth_total": "1",
            "11101_death_total": "1",
            "11102_birth_total": "0",
            "11102_death_total": "0",
            "11103_birth_total": "1",
            "11103_death_total": "4",
            "11104_birth_total": "2",
            "11104_death_total": "0",
            "11105_birth_total": "1",
            "11105_death_total": "0",
            "new_population": 6,
            "sum_population": -1
        },
        "厚生里": {
            "11012": "3253",
            "11104": "3250",
            "11105": "3248",
            "11101_birth_total": "0",
            "11101_death_total": "2",
            "11102_birth_total": "0",
            "11102_death_total": "2",
            "11103_birth_total": "2",
            "11103_death_total": "0",
            "11104_birth_total": "0",
            "11104_death_total": "0",
            "11105_birth_total": "1",
            "11105_death_total": "2",
            "new_population": -2,
            "sum_population": -5
        },
        "清溪里": {
            "11012": "4807",
            "11104": "4802",
            "11105": "4802",
            "11101_birth_total": "3",
            "11101_death_total": "5",
            "11102_birth_total": "2",
            "11102_death_total": "3",
            "11103_birth_total": "1",
            "11103_death_total": "2",
            "11104_birth_total": "2",
            "11104_death_total": "2",
            "11105_birth_total": "2",
            "11105_death_total": "1",
            "new_population": 0,
            "sum_population": -5
        },
        "光榮里": {
            "11012": "1865",
            "11104": "1857",
            "11105": "1856",
            "11101_birth_total": "0",
            "11101_death_total": "5",
            "11102_birth_total": "0",
            "11102_death_total": "1",
            "11103_birth_total": "0",
            "11103_death_total": "2",
            "11104_birth_total": "0",
            "11104_death_total": "3",
            "11105_birth_total": "0",
            "11105_death_total": "3",
            "new_population": -1,
            "sum_population": -9
        },
        "斯文里": {
            "11012": "2217",
            "11104": "2211",
            "11105": "2208",
            "11101_birth_total": "2",
            "11101_death_total": "1",
            "11102_birth_total": "0",
            "11102_death_total": "4",
            "11103_birth_total": "0",
            "11103_death_total": "1",
            "11104_birth_total": "1",
            "11104_death_total": "1",
            "11105_birth_total": "1",
            "11105_death_total": "3",
            "new_population": -3,
            "sum_population": -9
        },
        "新興里": {
            "11012": "2922",
            "11104": "2905",
            "11105": "2912",
            "11101_birth_total": "7",
            "11101_death_total": "1",
            "11102_birth_total": "2",
            "11102_death_total": "4",
            "11103_birth_total": "2",
            "11103_death_total": "3",
            "11104_birth_total": "1",
            "11104_death_total": "0",
            "11105_birth_total": "4",
            "11105_death_total": "2",
            "new_population": 7,
            "sum_population": -10
        },
        "湖西里": {
            "11012": "1684",
            "11104": "1672",
            "11105": "1672",
            "11101_birth_total": "1",
            "11101_death_total": "2",
            "11102_birth_total": "0",
            "11102_death_total": "2",
            "11103_birth_total": "0",
            "11103_death_total": "0",
            "11104_birth_total": "1",
            "11104_death_total": "2",
            "11105_birth_total": "2",
            "11105_death_total": "1",
            "new_population": 0,
            "sum_population": -12
        },
        "大同里": {
            "11012": "1911",
            "11104": "1901",
            "11105": "1899",
            "11101_birth_total": "2",
            "11101_death_total": "1",
            "11102_birth_total": "1",
            "11102_death_total": "1",
            "11103_birth_total": "3",
            "11103_death_total": "2",
            "11104_birth_total": "0",
            "11104_death_total": "2",
            "11105_birth_total": "0",
            "11105_death_total": "3",
            "new_population": -2,
            "sum_population": -12
        },
        "歸心里": {
            "11012": "1228",
            "11104": "1215",
            "11105": "1214",
            "11101_birth_total": "1",
            "11101_death_total": "0",
            "11102_birth_total": "0",
            "11102_death_total": "1",
            "11103_birth_total": "3",
            "11103_death_total": "3",
            "11104_birth_total": "0",
            "11104_death_total": "0",
            "11105_birth_total": "0",
            "11105_death_total": "1",
            "new_population": -1,
            "sum_population": -14
        },
        "永光里": {
            "11012": "1619",
            "11104": "1613",
            "11105": "1605",
            "11101_birth_total": "1",
            "11101_death_total": "2",
            "11102_birth_total": "1",
            "11102_death_total": "3",
            "11103_birth_total": "0",
            "11103_death_total": "1",
            "11104_birth_total": "1",
            "11104_death_total": "3",
            "11105_birth_total": "0",
            "11105_death_total": "7",
            "new_population": -8,
            "sum_population": -14
        },
        "橋北里": {
            "11012": "1150",
            "11104": "1137",
            "11105": "1135",
            "11101_birth_total": "0",
            "11101_death_total": "1",
            "11102_birth_total": "1",
            "11102_death_total": "0",
            "11103_birth_total": "0",
            "11103_death_total": "0",
            "11104_birth_total": "1",
            "11104_death_total": "0",
            "11105_birth_total": "2",
            "11105_death_total": "2",
            "new_population": -2,
            "sum_population": -15
        },
        "大埔里": {
            "11012": "1833",
            "11104": "1825",
            "11105": "1818",
            "11101_birth_total": "1",
            "11101_death_total": "4",
            "11102_birth_total": "1",
            "11102_death_total": "2",
            "11103_birth_total": "0",
            "11103_death_total": "1",
            "11104_birth_total": "0",
            "11104_death_total": "0",
            "11105_birth_total": "0",
            "11105_death_total": "4",
            "new_population": -7,
            "sum_population": -15
        },
        "海豐里": {
            "11012": "980",
            "11104": "975",
            "11105": "964",
            "11101_birth_total": "0",
            "11101_death_total": "1",
            "11102_birth_total": "1",
            "11102_death_total": "5",
            "11103_birth_total": "1",
            "11103_death_total": "0",
            "11104_birth_total": "0",
            "11104_death_total": "0",
            "11105_birth_total": "0",
            "11105_death_total": "1",
            "new_population": -11,
            "sum_population": -16
        },
        "大洲里": {
            "11012": "1327",
            "11104": "1314",
            "11105": "1311",
            "11101_birth_total": "1",
            "11101_death_total": "0",
            "11102_birth_total": "1",
            "11102_death_total": "1",
            "11103_birth_total": "0",
            "11103_death_total": "0",
            "11104_birth_total": "2",
            "11104_death_total": "2",
            "11105_birth_total": "0",
            "11105_death_total": "1",
            "new_population": -3,
            "sum_population": -16
        },
        "崇武里": {
            "11012": "4744",
            "11104": "4715",
            "11105": "4727",
            "11101_birth_total": "4",
            "11101_death_total": "5",
            "11102_birth_total": "3",
            "11102_death_total": "9",
            "11103_birth_total": "1",
            "11103_death_total": "4",
            "11104_birth_total": "2",
            "11104_death_total": "3",
            "11105_birth_total": "3",
            "11105_death_total": "2",
            "new_population": 12,
            "sum_population": -17
        },
        "建國里": {
            "11012": "1929",
            "11104": "1922",
            "11105": "1911",
            "11101_birth_total": "0",
            "11101_death_total": "3",
            "11102_birth_total": "0",
            "11102_death_total": "5",
            "11103_birth_total": "0",
            "11103_death_total": "3",
            "11104_birth_total": "1",
            "11104_death_total": "0",
            "11105_birth_total": "0",
            "11105_death_total": "4",
            "new_population": -11,
            "sum_population": -18
        },
        "長春里": {
            "11012": "2043",
            "11104": "2019",
            "11105": "2024",
            "11101_birth_total": "0",
            "11101_death_total": "1",
            "11102_birth_total": "0",
            "11102_death_total": "3",
            "11103_birth_total": "0",
            "11103_death_total": "1",
            "11104_birth_total": "0",
            "11104_death_total": "2",
            "11105_birth_total": "1",
            "11105_death_total": "0",
            "new_population": 5,
            "sum_population": -19
        },
        "前進里": {
            "11012": "3315",
            "11104": "3302",
            "11105": "3295",
            "11101_birth_total": "1",
            "11101_death_total": "2",
            "11102_birth_total": "3",
            "11102_death_total": "1",
            "11103_birth_total": "1",
            "11103_death_total": "3",
            "11104_birth_total": "0",
            "11104_death_total": "2",
            "11105_birth_total": "2",
            "11105_death_total": "6",
            "new_population": -7,
            "sum_population": -20
        },
        "楠樹里": {
            "11012": "2274",
            "11104": "2256",
            "11105": "2254",
            "11101_birth_total": "0",
            "11101_death_total": "2",
            "11102_birth_total": "1",
            "11102_death_total": "4",
            "11103_birth_total": "1",
            "11103_death_total": "0",
            "11104_birth_total": "0",
            "11104_death_total": "3",
            "11105_birth_total": "0",
            "11105_death_total": "6",
            "new_population": -2,
            "sum_population": -20
        },
        "大湖里": {
            "11012": "1996",
            "11104": "1978",
            "11105": "1974",
            "11101_birth_total": "0",
            "11101_death_total": "2",
            "11102_birth_total": "1",
            "11102_death_total": "0",
            "11103_birth_total": "1",
            "11103_death_total": "1",
            "11104_birth_total": "0",
            "11104_death_total": "2",
            "11105_birth_total": "2",
            "11105_death_total": "2",
            "new_population": -4,
            "sum_population": -22
        },
        "一心里": {
            "11012": "2150",
            "11104": "2131",
            "11105": "2126",
            "11101_birth_total": "0",
            "11101_death_total": "2",
            "11102_birth_total": "1",
            "11102_death_total": "1",
            "11103_birth_total": "2",
            "11103_death_total": "5",
            "11104_birth_total": "1",
            "11104_death_total": "1",
            "11105_birth_total": "3",
            "11105_death_total": "3",
            "new_population": -5,
            "sum_population": -24
        },
        "仁義里": {
            "11012": "1244",
            "11104": "1222",
            "11105": "1220",
            "11101_birth_total": "0",
            "11101_death_total": "0",
            "11102_birth_total": "0",
            "11102_death_total": "0",
            "11103_birth_total": "1",
            "11103_death_total": "1",
            "11104_birth_total": "0",
            "11104_death_total": "3",
            "11105_birth_total": "1",
            "11105_death_total": "0",
            "new_population": -2,
            "sum_population": -24
        },
        "安鎮里": {
            "11012": "2304",
            "11104": "2283",
            "11105": "2277",
            "11101_birth_total": "0",
            "11101_death_total": "2",
            "11102_birth_total": "2",
            "11102_death_total": "3",
            "11103_birth_total": "2",
            "11103_death_total": "3",
            "11104_birth_total": "0",
            "11104_death_total": "0",
            "11105_birth_total": "2",
            "11105_death_total": "2",
            "new_population": -6,
            "sum_population": -27
        },
        "空翔里": {
            "11012": "4380",
            "11104": "4374",
            "11105": "4353",
            "11101_birth_total": "2",
            "11101_death_total": "3",
            "11102_birth_total": "0",
            "11102_death_total": "7",
            "11103_birth_total": "1",
            "11103_death_total": "4",
            "11104_birth_total": "2",
            "11104_death_total": "3",
            "11105_birth_total": "2",
            "11105_death_total": "6",
            "new_population": -21,
            "sum_population": -27
        },
        "義勇里": {
            "11012": "2005",
            "11104": "1993",
            "11105": "1978",
            "11101_birth_total": "0",
            "11101_death_total": "4",
            "11102_birth_total": "0",
            "11102_death_total": "1",
            "11103_birth_total": "0",
            "11103_death_total": "4",
            "11104_birth_total": "0",
            "11104_death_total": "1",
            "11105_birth_total": "1",
            "11105_death_total": "3",
            "new_population": -15,
            "sum_population": -27
        },
        "橋南里": {
            "11012": "1743",
            "11104": "1716",
            "11105": "1712",
            "11101_birth_total": "0",
            "11101_death_total": "1",
            "11102_birth_total": "1",
            "11102_death_total": "2",
            "11103_birth_total": "1",
            "11103_death_total": "2",
            "11104_birth_total": "0",
            "11104_death_total": "0",
            "11105_birth_total": "0",
            "11105_death_total": "2",
            "new_population": -4,
            "sum_population": -31
        },
        "公園里": {
            "11012": "2252",
            "11104": "2235",
            "11105": "2221",
            "11101_birth_total": "0",
            "11101_death_total": "2",
            "11102_birth_total": "0",
            "11102_death_total": "1",
            "11103_birth_total": "1",
            "11103_death_total": "3",
            "11104_birth_total": "0",
            "11104_death_total": "0",
            "11105_birth_total": "0",
            "11105_death_total": "3",
            "new_population": -14,
            "sum_population": -31
        },
        "豐榮里": {
            "11012": "2820",
            "11104": "2792",
            "11105": "2783",
            "11101_birth_total": "0",
            "11101_death_total": "1",
            "11102_birth_total": "1",
            "11102_death_total": "1",
            "11103_birth_total": "2",
            "11103_death_total": "1",
            "11104_birth_total": "1",
            "11104_death_total": "1",
            "11105_birth_total": "0",
            "11105_death_total": "1",
            "new_population": -9,
            "sum_population": -37
        },
        "崇蘭里": {
            "11012": "9685",
            "11104": "9628",
            "11105": "9640",
            "11101_birth_total": "4",
            "11101_death_total": "3",
            "11102_birth_total": "1",
            "11102_death_total": "2",
            "11103_birth_total": "4",
            "11103_death_total": "5",
            "11104_birth_total": "2",
            "11104_death_total": "2",
            "11105_birth_total": "7",
            "11105_death_total": "7",
            "new_population": 12,
            "sum_population": -45
        },
        "永城里": {
            "11012": "2547",
            "11104": "2503",
            "11105": "2501",
            "11101_birth_total": "0",
            "11101_death_total": "3",
            "11102_birth_total": "2",
            "11102_death_total": "4",
            "11103_birth_total": "2",
            "11103_death_total": "3",
            "11104_birth_total": "0",
            "11104_death_total": "1",
            "11105_birth_total": "0",
            "11105_death_total": "4",
            "new_population": -2,
            "sum_population": -46
        },
        "廣興里": {
            "11012": "3451",
            "11104": "3421",
            "11105": "3402",
            "11101_birth_total": "1",
            "11101_death_total": "2",
            "11102_birth_total": "0",
            "11102_death_total": "5",
            "11103_birth_total": "1",
            "11103_death_total": "4",
            "11104_birth_total": "0",
            "11104_death_total": "3",
            "11105_birth_total": "0",
            "11105_death_total": "6",
            "new_population": -19,
            "sum_population": -49
        },
        "崇陽里": {
            "11012": "8540",
            "11104": "8497",
            "11105": "8491",
            "11101_birth_total": "5",
            "11101_death_total": "1",
            "11102_birth_total": "5",
            "11102_death_total": "1",
            "11103_birth_total": "4",
            "11103_death_total": "4",
            "11104_birth_total": "3",
            "11104_death_total": "0",
            "11105_birth_total": "2",
            "11105_death_total": "1",
            "new_population": -6,
            "sum_population": -49
        },
        "北興里": {
            "11012": "7348",
            "11104": "7310",
            "11105": "7299",
            "11101_birth_total": "1",
            "11101_death_total": "3",
            "11102_birth_total": "0",
            "11102_death_total": "1",
            "11103_birth_total": "4",
            "11103_death_total": "2",
            "11104_birth_total": "2",
            "11104_death_total": "6",
            "11105_birth_total": "5",
            "11105_death_total": "7",
            "new_population": -11,
            "sum_population": -49
        },
        "仁愛里": {
            "11012": "2409",
            "11104": "2352",
            "11105": "2358",
            "11101_birth_total": "2",
            "11101_death_total": "5",
            "11102_birth_total": "0",
            "11102_death_total": "3",
            "11103_birth_total": "0",
            "11103_death_total": "2",
            "11104_birth_total": "1",
            "11104_death_total": "2",
            "11105_birth_total": "0",
            "11105_death_total": "1",
            "new_population": 6,
            "sum_population": -51
        },
        "中正里": {
            "11012": "5233",
            "11104": "5184",
            "11105": "5176",
            "11101_birth_total": "3",
            "11101_death_total": "3",
            "11102_birth_total": "1",
            "11102_death_total": "2",
            "11103_birth_total": "3",
            "11103_death_total": "1",
            "11104_birth_total": "1",
            "11104_death_total": "5",
            "11105_birth_total": "1",
            "11105_death_total": "6",
            "new_population": -8,
            "sum_population": -57
        },
        "潭墘里": {
            "11012": "6191",
            "11104": "6153",
            "11105": "6134",
            "11101_birth_total": "2",
            "11101_death_total": "6",
            "11102_birth_total": "5",
            "11102_death_total": "3",
            "11103_birth_total": "3",
            "11103_death_total": "5",
            "11104_birth_total": "0",
            "11104_death_total": "4",
            "11105_birth_total": "2",
            "11105_death_total": "6",
            "new_population": -19,
            "sum_population": -57
        },
        "瑞光里": {
            "11012": "8438",
            "11104": "8401",
            "11105": "8378",
            "11101_birth_total": "1",
            "11101_death_total": "9",
            "11102_birth_total": "3",
            "11102_death_total": "6",
            "11103_birth_total": "3",
            "11103_death_total": "5",
            "11104_birth_total": "1",
            "11104_death_total": "5",
            "11105_birth_total": "3",
            "11105_death_total": "10",
            "new_population": -23,
            "sum_population": -60
        },
        "華山里": {
            "11012": "5796",
            "11104": "5756",
            "11105": "5733",
            "11101_birth_total": "2",
            "11101_death_total": "4",
            "11102_birth_total": "4",
            "11102_death_total": "7",
            "11103_birth_total": "5",
            "11103_death_total": "5",
            "11104_birth_total": "3",
            "11104_death_total": "3",
            "11105_birth_total": "3",
            "11105_death_total": "5",
            "new_population": -23,
            "sum_population": -63
        },
        "新生里": {
            "11012": "6226",
            "11104": "6165",
            "11105": "6161",
            "11101_birth_total": "3",
            "11101_death_total": "2",
            "11102_birth_total": "2",
            "11102_death_total": "7",
            "11103_birth_total": "4",
            "11103_death_total": "3",
            "11104_birth_total": "1",
            "11104_death_total": "3",
            "11105_birth_total": "1",
            "11105_death_total": "5",
            "new_population": -4,
            "sum_population": -65
        },
        "溝美里": {
            "11012": "2627",
            "11104": "2566",
            "11105": "2562",
            "11101_birth_total": "0",
            "11101_death_total": "2",
            "11102_birth_total": "1",
            "11102_death_total": "3",
            "11103_birth_total": "0",
            "11103_death_total": "1",
            "11104_birth_total": "2",
            "11104_death_total": "5",
            "11105_birth_total": "2",
            "11105_death_total": "3",
            "new_population": -4,
            "sum_population": -65
        },
        "豐源里": {
            "11012": "4280",
            "11104": "4232",
            "11105": "4212",
            "11101_birth_total": "2",
            "11101_death_total": "2",
            "11102_birth_total": "2",
            "11102_death_total": "2",
            "11103_birth_total": "4",
            "11103_death_total": "1",
            "11104_birth_total": "0",
            "11104_death_total": "6",
            "11105_birth_total": "1",
            "11105_death_total": "6",
            "new_population": -20,
            "sum_population": -68
        },
        "維新里": {
            "11012": "2867",
            "11104": "2800",
            "11105": "2799",
            "11101_birth_total": "1",
            "11101_death_total": "3",
            "11102_birth_total": "1",
            "11102_death_total": "5",
            "11103_birth_total": "2",
            "11103_death_total": "4",
            "11104_birth_total": "0",
            "11104_death_total": "7",
            "11105_birth_total": "1",
            "11105_death_total": "3",
            "new_population": -1,
            "sum_population": -68
        },
        "勝利里": {
            "11012": "6458",
            "11104": "6408",
            "11105": "6387",
            "11101_birth_total": "3",
            "11101_death_total": "6",
            "11102_birth_total": "0",
            "11102_death_total": "5",
            "11103_birth_total": "0",
            "11103_death_total": "9",
            "11104_birth_total": "2",
            "11104_death_total": "4",
            "11105_birth_total": "2",
            "11105_death_total": "8",
            "new_population": -21,
            "sum_population": -71
        },
        "豐田里": {
            "11012": "4741",
            "11104": "4668",
            "11105": "4665",
            "11101_birth_total": "0",
            "11101_death_total": "3",
            "11102_birth_total": "0",
            "11102_death_total": "3",
            "11103_birth_total": "3",
            "11103_death_total": "3",
            "11104_birth_total": "0",
            "11104_death_total": "3",
            "11105_birth_total": "3",
            "11105_death_total": "5",
            "new_population": -3,
            "sum_population": -76
        },
        "豐年里": {
            "11012": "5827",
            "11104": "5759",
            "11105": "5742",
            "11101_birth_total": "0",
            "11101_death_total": "3",
            "11102_birth_total": "1",
            "11102_death_total": "1",
            "11103_birth_total": "0",
            "11103_death_total": "1",
            "11104_birth_total": "0",
            "11104_death_total": "5",
            "11105_birth_total": "1",
            "11105_death_total": "2",
            "new_population": -17,
            "sum_population": -85
        },
        "大連里": {
            "11012": "4811",
            "11104": "4736",
            "11105": "4722",
            "11101_birth_total": "0",
            "11101_death_total": "3",
            "11102_birth_total": "0",
            "11102_death_total": "3",
            "11103_birth_total": "1",
            "11103_death_total": "3",
            "11104_birth_total": "1",
            "11104_death_total": "3",
            "11105_birth_total": "1",
            "11105_death_total": "1",
            "new_population": -14,
            "sum_population": -89
        },
        "大武里": {
            "11012": "9419",
            "11104": "9305",
            "11105": "9276",
            "11101_birth_total": "2",
            "11101_death_total": "5",
            "11102_birth_total": "0",
            "11102_death_total": "4",
            "11103_birth_total": "3",
            "11103_death_total": "5",
            "11104_birth_total": "4",
            "11104_death_total": "1",
            "11105_birth_total": "3",
            "11105_death_total": "6",
            "new_population": -29,
            "sum_population": -143
        }
    }
}